orbis_plugin_evaluation_binary_classification_evaluation/__init__.py
orbis_plugin_evaluation_binary_classification_evaluation/main.py
orbis_plugin_evaluation_binary_classification_evaluation-2.3.0.dist-info/LICENSE
orbis_plugin_evaluation_binary_classification_evaluation-2.3.0.dist-info/METADATA
orbis_plugin_evaluation_binary_classification_evaluation-2.3.0.dist-info/WHEEL
orbis_plugin_evaluation_binary_classification_evaluation-2.3.0.dist-info/top_level.txt
orbis_plugin_evaluation_binary_classification_evaluation-2.3.0.dist-info/RECORD
