Metadata-Version: 2.1
Name: orbis-plugin-evaluation-binary-classification-evaluation
Version: 2.3.0
Summary: The binary_classification_evaluation evaluation plugin for Orbis
Home-page: https://github.com/orbis-eval/orbis_plugin_evaluation_binary_classification_evaluation
Author: fabod
License: GPL2
Platform: UNKNOWN
Requires-Python: >3.6
